link/__init__.py
link/crdt/__init__.py
link/crdt/core.py
link/crdt/counter.py
link/crdt/diff.py
link/crdt/flag.py
link/crdt/map.py
link/crdt/register.py
link/crdt/set.py
link/crdt/utils.py
link/crdt/test/__init__.py
link/crdt/test/base.py
link/crdt/test/core.py
link/crdt/test/counter.py
link/crdt/test/diff.py
link/crdt/test/flag.py
link/crdt/test/map.py
link/crdt/test/register.py
link/crdt/test/set.py
link/crdt/test/utils.py
link.crdt-1.0.dist-info/DESCRIPTION.rst
link.crdt-1.0.dist-info/METADATA
link.crdt-1.0.dist-info/RECORD
link.crdt-1.0.dist-info/WHEEL
link.crdt-1.0.dist-info/metadata.json
link.crdt-1.0.dist-info/top_level.txt
