Metadata-Version: 2.0
Name: link.crdt
Version: 1.0
Summary: Python implementation of Convergent Replicated Data Types
Home-page: https://github.com/linkdd/link.utils
Author: David Delassus
Author-email: david.jose.delassus@gmail.com
License: MIT
Keywords: link convergent replicated data types
Platform: UNKNOWN
Classifier: Development Status :: 5 - Production/Stable
Classifier: License :: OSI Approved :: MIT License
Classifier: Operating System :: OS Independent
Classifier: Topic :: Utilities
Classifier: Topic :: Software Development :: Libraries :: Python Modules
Classifier: Intended Audience :: Developers
Classifier: Programming Language :: Python
Classifier: Programming Language :: Python :: 2.7
Classifier: Programming Language :: Python :: 3
Classifier: Programming Language :: Python :: 3.4
Classifier: Programming Language :: Python :: 3.5
Classifier: Programming Language :: Python :: Implementation :: CPython
Requires-Dist: six (>=1.10.0)
